charfield_filters/__init__.py
charfield_filters/admin.py
charfield_filters/filters.py
charfield_filters/tests.py
charfield_filters/templates/admin/charfield_filters/autocomplete_filter.html
charfield_filters/templates/admin/charfield_filters/autocomplete_select_filter.html
charfield_filters/templates/admin/charfield_filters/dropdown_filter.html
django_charfield_filters-0.1.3.dist-info/LICENSE
django_charfield_filters-0.1.3.dist-info/METADATA
django_charfield_filters-0.1.3.dist-info/WHEEL
django_charfield_filters-0.1.3.dist-info/top_level.txt
django_charfield_filters-0.1.3.dist-info/RECORD
